Metadata-Version: 2.1
Name: bookish
Version: 1.2
Summary: Word count for text
Home-page: https://github.com/iratigaritano/bookish
Author: Irati Garitano, Javier Ortega
Author-email: irati.garitano@alumni.mondragon.edu, javier.ortega@alumni.mondragon.edu
License: MIT
Download-URL: https://github.com/iratigaritano/bookish/archive/refs/tags/v_12.tar.gz
Keywords: WORD,COUNT,BOOK
Platform: UNKNOWN
Classifier: Development Status :: 3 - Alpha
Classifier: Intended Audience :: Developers
Classifier: Topic :: Software Development :: Build Tools
Classifier: License :: OSI Approved :: MIT License
Classifier: Programming Language :: Python :: 3
Classifier: Programming Language :: Python :: 3.4
Classifier: Programming Language :: Python :: 3.5
Classifier: Programming Language :: Python :: 3.6
